nonebot_plugin_bafortune/__init__.py
nonebot_plugin_bafortune/api.py
nonebot_plugin_bafortune/config.py
nonebot_plugin_bafortune/data.py
nonebot_plugin_bafortune-1.0.8.dist-info/LICENSE
nonebot_plugin_bafortune-1.0.8.dist-info/WHEEL
nonebot_plugin_bafortune-1.0.8.dist-info/METADATA
nonebot_plugin_bafortune-1.0.8.dist-info/RECORD
