Metadata-Version: 2.1
Name: nonebot-plugin-bafortune
Version: 1.0.8
Summary: 蔚蓝档案今日运势插件, BlueArchive fortune plugin
Home-page: https://github.com/captain-wangrun-cn/nonebot-plugin-bafortune
License: GPL-3.0
Author: WR
Author-email: wangrun114514@foxmail.com
Requires-Python: >=3.9,<4.0
Classifier: License :: OSI Approved :: GNU General Public License v3 (GPLv3)
Classifier: Programming Language :: Python :: 3
Classifier: Programming Language :: Python :: 3.10
Classifier: Programming Language :: Python :: 3.9
Requires-Dist: httpx (>=0.27.0,<1.0.0)
Requires-Dist: nonebot-adapter-onebot (>=2.0.0,<3.0.0)
Requires-Dist: nonebot-plugin-alconna (>=0.46.3)
Requires-Dist: nonebot-plugin-localstore (>=0.7.3,<0.8.0)
Requires-Dist: nonebot-plugin-uninfo (>=0.6.1)
Requires-Dist: nonebot2 (>=2.2.0,<3.0.0)
Project-URL: Repository, https://github.com/captain-wangrun-cn/nonebot-plugin-bafortune
